idrive_e2/__init__.py
idrive_e2/client.py
idrive_e2/errors.py
idrive_e2/py.typed
idrive_e2_client-0.1.0.dist-info/licenses/LICENSE
idrive_e2_client-0.1.0.dist-info/METADATA
idrive_e2_client-0.1.0.dist-info/WHEEL
idrive_e2_client-0.1.0.dist-info/top_level.txt
idrive_e2_client-0.1.0.dist-info/RECORD
