Metadata-Version: 2.4
Name: idrive-e2-client
Version: 0.1.0
Summary: Async Python client for the IDrive e2 Get Region Endpoint API (returns only endpoint URL).
Author: Patrick Vorgers
Maintainer: Patrick Vorgers
License: MIT
Project-URL: Homepage, https://github.com/patrickvorgers/idrive-e2-client
Project-URL: Repository, https://github.com/patrickvorgers/idrive-e2-client
Project-URL: Issues, https://github.com/patrickvorgers/idrive-e2-client/issues
Project-URL: Changelog, https://github.com/patrickvorgers/idrive-e2-client/releases
Keywords: idrive,e2,s3,region,client,async,aiohttp
Classifier: Programming Language :: Python :: 3
Classifier: Programming Language :: Python :: 3 :: Only
Classifier: Programming Language :: Python :: 3.11
Classifier: License :: OSI Approved :: MIT License
Classifier: Topic :: Internet
Classifier: Framework :: AsyncIO
Classifier: Intended Audience :: Developers
Classifier: Operating System :: OS Independent
Requires-Python: >=3.11
License-File: LICENSE
Requires-Dist: aiohttp>=3.9
Requires-Dist: typing-extensions>=4.9.0
Provides-Extra: dev
Requires-Dist: pytest>=8.0; extra == "dev"
Requires-Dist: pytest-asyncio>=0.23; extra == "dev"
Requires-Dist: aioresponses>=0.7.6; extra == "dev"
Requires-Dist: ruff>=0.5.0; extra == "dev"
Requires-Dist: mypy>=1.9.0; extra == "dev"
Dynamic: license-file
